searchlet/Environment.py
searchlet/__init__.py
searchlet/algorithms/AStar.py
searchlet/algorithms/BFS.py
searchlet/algorithms/DFS.py
searchlet/algorithms/Dijkstra.py
searchlet/algorithms/IDAStar.py
searchlet/algorithms/IDDFS.py
searchlet/algorithms/SearchAlgorithm.py
searchlet/algorithms/__init__.py
searchlet/ds/PriorityQueue.py
searchlet/ds/Stack.py
searchlet/ds/__init__.py
searchlet/environments/Grid.py
searchlet/environments/__init__.py
searchlet/test/__init__.py
searchlet/test/test_astar.py
searchlet/test/test_bfs.py
searchlet/test/test_dfs.py
searchlet/test/test_iddfs.py
searchlet/utils/__init__.py
searchlet/utils/explore.py
searchlet-1.0.1.dist-info/METADATA
searchlet-1.0.1.dist-info/RECORD
searchlet-1.0.1.dist-info/WHEEL
searchlet-1.0.1.dist-info/top_level.txt
