Metadata-Version: 2.1
Name: searchlet
Version: 1.0.1
Summary: Python Search Algorithms
Home-page: https://github.com/DavidMChan/searchlet
Author: David Chan
Author-email: davidchan@berkeley.edu
License: MIT License
Requires-Dist: pytest (>=3.7.0)
